proxtract/__init__.py
proxtract/__main__.py
proxtract/config.py
proxtract/core.py
proxtract/main.py
proxtract/state.py
proxtract/tui/__init__.py
proxtract/tui/app.py
proxtract/tui/styles.tcss
proxtract/tui/screens/__init__.py
proxtract/tui/screens/edit_setting_screen.py
proxtract/tui/screens/extract_screen.py
proxtract/tui/screens/main_screen.py
proxtract/tui/widgets/__init__.py
proxtract/tui/widgets/action_item.py
proxtract/tui/widgets/completion_input.py
proxtract/tui/widgets/setting_item.py
proxtract/tui/widgets/summary_display.py
proxtract-0.2.22.dist-info/licenses/LICENSE
proxtract-0.2.22.dist-info/METADATA
proxtract-0.2.22.dist-info/WHEEL
proxtract-0.2.22.dist-info/entry_points.txt
proxtract-0.2.22.dist-info/top_level.txt
proxtract-0.2.22.dist-info/RECORD
