Metadata-Version: 2.4
Name: proxtract
Version: 0.2.22
Summary: Interactive CLI to extract project files into a single bundle
Author: Proxtract Team
License-Expression: MIT
Keywords: cli,developer-tools,prompt-engineering,project-extraction
Classifier: Development Status :: 3 - Alpha
Classifier: Intended Audience :: Developers
Classifier: Environment :: Console
Classifier: Programming Language :: Python :: 3
Classifier: Programming Language :: Python :: 3.9
Classifier: Programming Language :: Python :: 3.10
Classifier: Programming Language :: Python :: 3.11
Classifier: Programming Language :: Python :: 3.12
Classifier: Operating System :: OS Independent
Requires-Python: >=3.9
License-File: LICENSE
Requires-Dist: rich>=13.7.0
Requires-Dist: textual>=0.60
Requires-Dist: pathspec>=0.11
Requires-Dist: tiktoken>=0.7
Requires-Dist: argcomplete>=3.1.4
Provides-Extra: banner
Requires-Dist: art>=6.0; extra == "banner"
Provides-Extra: gitignore
Requires-Dist: pathspec>=0.11; extra == "gitignore"
Provides-Extra: tokens
Requires-Dist: tiktoken>=0.7; extra == "tokens"
Provides-Extra: clipboard
Requires-Dist: pyperclip>=1.8; extra == "clipboard"
Provides-Extra: config
Requires-Dist: tomli>=2.0; extra == "config"
Provides-Extra: all
Requires-Dist: art>=6.0; extra == "all"
Requires-Dist: pathspec>=0.11; extra == "all"
Requires-Dist: tiktoken>=0.7; extra == "all"
Requires-Dist: pyperclip>=1.8; extra == "all"
Requires-Dist: tomli>=2.0; extra == "all"
Requires-Dist: argcomplete>=3.1.4; extra == "all"
Provides-Extra: dev
Requires-Dist: build>=1.0.3; extra == "dev"
Requires-Dist: twine>=4.0.2; extra == "dev"
Requires-Dist: pytest>=7.0.0; extra == "dev"
Requires-Dist: pytest-cov>=4.0.0; extra == "dev"
Requires-Dist: pytest-mock>=3.10.0; extra == "dev"
Dynamic: license-file
